downtube/__init__.py
downtube/main.py
downtube-0.1.6.dist-info/entry_points.txt
downtube-0.1.6.dist-info/LICENSE
downtube-0.1.6.dist-info/WHEEL
downtube-0.1.6.dist-info/METADATA
downtube-0.1.6.dist-info/RECORD
