Metadata-Version: 2.1
Name: downtube
Version: 0.1.6
Summary: A simple yet powerful youtube downloader built in python
Home-page: https://github.com/arghyagod-coder/downtube
License: MIT
Keywords: Downtube,youtube-downloader,download,youtube
Author: Arghya Sarkar
Author-email: arghyasarkar.nolan@gmail.com
Requires-Python: >=3.9,<4.0
Classifier: License :: OSI Approved :: MIT License
Classifier: Operating System :: OS Independent
Classifier: Programming Language :: Python :: 3
Classifier: Programming Language :: Python :: 3.6
Classifier: Programming Language :: Python :: 3.7
Classifier: Programming Language :: Python :: 3.8
Classifier: Programming Language :: Python :: 3.9
Requires-Dist: click (>=8.0.1,<9.0.0)
Requires-Dist: click-help-colors (>=0.9.1,<0.10.0)
Requires-Dist: pytube (>=10.9.2,<11.0.0)
Requires-Dist: tqdm (>=4.61.2,<5.0.0)
Requires-Dist: youtube-search (>=2.1.0,<3.0.0)
Project-URL: Repository, https://github.com/arghyagod-coder/downtube
